django_yamlconf/__init__.py
django_yamlconf/urls.py
django_yamlconf/views.py
django_yamlconf/management/__init__.py
django_yamlconf/management/commands/__init__.py
django_yamlconf/management/commands/ycexplain.py
django_yamlconf/management/commands/yclist.py
django_yamlconf/management/commands/ycsysfiles.py
django_yamlconf/static/yamlconf/yamlconf.css
django_yamlconf/templates/yamlconf/attribute.html
django_yamlconf/templates/yamlconf/base.html
django_yamlconf/templates/yamlconf/index.html
django_yamlconf/templates/yamlconf/value.html
django_yamlconf/templatetags/__init__.py
django_yamlconf/templatetags/yamconf_tags.py
django_yamlconf-1.5.0.dist-info/METADATA
django_yamlconf-1.5.0.dist-info/WHEEL
django_yamlconf-1.5.0.dist-info/licenses/LICENSE
django_yamlconf-1.5.0.dist-info/licenses/NOTICE
django_yamlconf-1.5.0.dist-info/RECORD
