Metadata-Version: 2.4
Name: django-yamlconf
Version: 1.5.0
Summary: Define Django settings in local YAML (or JSON) files
Project-URL: Homepage, https://django-yamlconf.readthedocs.io/en/latest/
Project-URL: Issues, https://github.com/vmware/django-yamlconf/issues
Author-email: Michael Rohan <michael.rohan@broadcom.com>
License-File: LICENSE
License-File: NOTICE
Classifier: Development Status :: 4 - Beta
Classifier: Framework :: Django
Classifier: Framework :: Django :: 3.0
Classifier: Framework :: Django :: 4.0
Classifier: Intended Audience :: Developers
Classifier: License :: OSI Approved :: BSD License
Classifier: Natural Language :: English
Classifier: Operating System :: OS Independent
Classifier: Programming Language :: Python
Classifier: Programming Language :: Python :: 3.5
Classifier: Topic :: Software Development :: Libraries :: Python Modules
Requires-Python: >=3.8
Requires-Dist: pyyaml>=3.10
